Metadata-Version: 2.1
Name: insightfacewrapper
Version: 0.0.4
Summary: Wrapper over insightface for a more convenient inference.
Home-page: https://github.com/ternaus/https://github.com/ternaus/insightfaceWrapper
Author: Vladimir Iglovikov
License: MIT
Platform: UNKNOWN
Classifier: License :: OSI Approved :: MIT License
Classifier: Intended Audience :: Developers
Classifier: Intended Audience :: Science/Research
Classifier: Operating System :: OS Independent
Classifier: Programming Language :: Python
Classifier: Programming Language :: Python :: 3
Classifier: Topic :: Software Development :: Libraries
Classifier: Topic :: Software Development :: Libraries :: Python Modules
Provides-Extra: test
License-File: LICENSE
